CHANGES
LICENSE
README.txt
bootstrap.py
buildout.cfg
setup.cfg
setup.py
iw/__init__.py
iw.rotatezlogs.egg-info/PKG-INFO
iw.rotatezlogs.egg-info/SOURCES.txt
iw.rotatezlogs.egg-info/dependency_links.txt
iw.rotatezlogs.egg-info/entry_points.txt
iw.rotatezlogs.egg-info/namespace_packages.txt
iw.rotatezlogs.egg-info/not-zip-safe
iw.rotatezlogs.egg-info/requires.txt
iw.rotatezlogs.egg-info/top_level.txt
iw/rotatezlogs/ABOUT
iw/rotatezlogs/CHANGES
iw/rotatezlogs/LICENSE
iw/rotatezlogs/LogHandlers.py
iw/rotatezlogs/README.txt
iw/rotatezlogs/TESTED_WITH
iw/rotatezlogs/TODO
iw/rotatezlogs/__init__.py
iw/rotatezlogs/component.xml
iw/rotatezlogs/datatypes.py
iw/rotatezlogs/version.txt
iw/rotatezlogs/docs/FAQ
iw/rotatezlogs/docs/README.txt
iw/rotatezlogs/docs/SCREENSHOTS
iw/rotatezlogs/docs/icon.png
iw/rotatezlogs/docs/log_folder.png
iw/rotatezlogs/docs/zope_conf.png
iw/rotatezlogs/doctests/README.txt
iw/rotatezlogs/ftests/README.txt
iw/rotatezlogs/ftests/minimaltest.py
iw/rotatezlogs/tests/README.txt
iw/rotatezlogs/tests/__init__.py
iw/rotatezlogs/tests/test_rotatezlogs.py
iw/rotatezlogs/tests/test_rotatezlogsdocs.py
iw/rotatezlogs/tests/test_rotatezlogsdocstrings.py