Metadata-Version: 1.0
Name: iw.rotatezlogs
Version: 0.1.2
Summary: Rotates Zope logs
Home-page: https://ingeniweb.svn.sourceforge.net/svnroot/ingeniweb/iw.rotatezlogs
Author: Ingeniweb
Author-email: support@ingeniweb.com
License: GPL
Platform: UNKNOWN
Classifier: Programming Language :: Python
Classifier: Topic :: System :: Logging
Classifier: Framework :: Zope2
